LICENSE
README.md
pybn.py
setup.py
pybn.egg-info/PKG-INFO
pybn.egg-info/SOURCES.txt
pybn.egg-info/dependency_links.txt
pybn.egg-info/top_level.txt