Metadata-Version: 2.1
Name: pybn
Version: 0.0.1
Summary: Python package for simple build number generation.
Home-page: https://github.com/CodeConfidant/pybn
Author: Drew Hainer
Author-email: codeconfidant@gmail.com
License: MIT
Platform: Windows
Platform: Linux
License-File: LICENSE
